colorpage/__init__.py
colorpage/package_data.dat
colorpage/shipwright.py
colorpage-1.0.0.data/data/my_data/data_file
colorpage-1.0.0.dist-info/LICENSE.txt
colorpage-1.0.0.dist-info/METADATA
colorpage-1.0.0.dist-info/WHEEL
colorpage-1.0.0.dist-info/entry_points.txt
colorpage-1.0.0.dist-info/top_level.txt
colorpage-1.0.0.dist-info/RECORD
